{
    "code": 0,
    "subcode": 0,
    "message": "",
    "default": 0,
    "data": {
        "uin": 0,
        "categoryId": 10000000,
        "sortId": 5,
        "sum": 6063,
        "sin": 0,
        "ein": 29,
        "list": [{
            "dissid": "3687088783",
            "createtime": "2018-02-08",
            "commit_time": "2018-02-08",
            "dissname": "苦涩回忆：歌词应景，连想念都很无力",
            "imgurl": "http://p.qpic.cn/music_cover/MhQ4bJBPt3Yt5icXyBGNhyIJibhCD2qU4ugiaA5BpuD1nnnliaKwSibQj8A/600?n=1",
            "introduction": "",
            "listennum": 320040,
            "score": 0,
            "version": 0,
            "creator": {
                "type": 0,
                "qq": 452775188,
                "encrypt_uin": "7e4A7iSkoKcF",
                "name": "还不是因为你长得不好看",
                "isVip": 0,
                "avatarUrl": "",
                "followflag": 0
            }
        }, {
            "dissid": "3809357345",
            "createtime": "2018-04-04",
            "commit_time": "2018-04-04",
            "dissname": "清吧音乐：惬意梦幻的巴萨诺瓦女声",
            "imgurl": "http://p.qpic.cn/music_cover/tmk5HNSnJvJhsOvcIpWulbrowia33pn5libLI3zj3a4Y2XOYZ66yeM5w/600?n=1",
            "introduction": "",
            "listennum": 482446,
            "score": 0,
            "version": 0,
            "creator": {
                "type": 2,
                "qq": 2958598324,
                "encrypt_uin": "owEkNe4qNeoA7n**",
                "name": "biG橘子",
                "isVip": 2,
                "avatarUrl": "",
                "followflag": 0
            }
        }, {
            "dissid": "3811971325",
            "createtime": "2018-04-04",
            "commit_time": "2018-04-04",
            "dissname": "小号后摇 | 沉溺于静默之海",
            "imgurl": "http://p.qpic.cn/music_cover/OxYJ3e12Q1MiaibkTa8iaSjoKTaj1NtVA1Rk1GthicialdKqgayDL4MIUuQ/600?n=1",
            "introduction": "",
            "listennum": 101774,
            "score": 0,
            "version": 0,
            "creator": {
                "type": 0,
                "qq": 3538848850,
                "encrypt_uin": "oi4iNecPNeckon**",
                "name": "趵突泉边上的小屁孩",
                "isVip": 0,
                "avatarUrl": "",
                "followflag": 0
            }
        }, {
            "dissid": "3283786927",
            "createtime": "2017-10-30",
            "commit_time": "2017-10-30",
            "dissname": "适合闺蜜在聊八卦时偷偷放的鼓点R&B",
            "imgurl": "http://p.qpic.cn/music_cover/UrAqTJyE9hXPTBJP3MVBYOUTPmX4OpD7icibjbrGpCzvV5JzSqibMHEibg/600?n=1",
            "introduction": "",
            "listennum": 197215,
            "score": 0,
            "version": 0,
            "creator": {
                "type": 0,
                "qq": 973995118,
                "encrypt_uin": "NKSiNKEkoK6F",
                "name": "eric",
                "isVip": 0,
                "avatarUrl": "",
                "followflag": 0
            }
        }, {
            "dissid": "3813200844",
            "createtime": "2018-04-04",
            "commit_time": "2018-04-04",
            "dissname": "欧美冷门唱作人精选",
            "imgurl": "http://p.qpic.cn/music_cover/tmk5HNSnJvJhsOvcIpWulbrowia33pn5leBSUrSx9Sh2CQ0YDVTU6ag/600?n=1",
            "introduction": "",
            "listennum": 15135,
            "score": 0,
            "version": 0,
            "creator": {
                "type": 2,
                "qq": 2958598324,
                "encrypt_uin": "owEkNe4qNeoA7n**",
                "name": "biG橘子",
                "isVip": 2,
                "avatarUrl": "",
                "followflag": 0
            }
        }, {
            "dissid": "3820664346",
            "createtime": "2018-04-10",
            "commit_time": "2018-04-10",
            "dissname": "清风若过：古风之安静治愈系",
            "imgurl": "http://p.qpic.cn/music_cover/n8Q2D61Euft2OPGVicqmNQmPXjtxyV0rNQw8JicyzDicicRGKvrco4lXNw/600?n=1",
            "introduction": "",
            "listennum": 75528,
            "score": 0,
            "version": 0,
            "creator": {
                "type": 0,
                "qq": 626616042,
                "encrypt_uin": "7w-s7w6soevA",
                "name": "玄觞",
                "isVip": 0,
                "avatarUrl": "",
                "followflag": 0
            }
        }, {
            "dissid": "3823672157",
            "createtime": "2018-04-10",
            "commit_time": "2018-04-10",
            "dissname": "撩姐小奶狗！韩剧姐弟恋盘点",
            "imgurl": "http://p.qpic.cn/music_cover/4fNUrZe1KnJJVic1Aq97mkt0bW1rhfibZo7jhq0D5kic1Wxibpc0GiaSiaBw/600?n=1",
            "introduction": "",
            "listennum": 42301,
            "score": 0,
            "version": 0,
            "creator": {
                "type": 2,
                "qq": 747867769,
                "encrypt_uin": "7ivlNeCl7iCq",
                "name": "JTY起风了",
                "isVip": 2,
                "avatarUrl": "",
                "followflag": 0
            }
        }, {
            "dissid": "3813116237",
            "createtime": "2018-04-10",
            "commit_time": "2018-04-10",
            "dissname": "日本UFO社动画歌曲精选",
            "imgurl": "http://p.qpic.cn/music_cover/zWAjtOcnpLTJ07iacJUgayibMf7wfmqlmgBXg19f1iawyZ9Kup5tgK3WQ/600?n=1",
            "introduction": "",
            "listennum": 20882,
            "score": 0,
            "version": 0,
            "creator": {
                "type": 2,
                "qq": 1250888122,
                "encrypt_uin": "oK-koecFNe6Aoc**",
                "name": "Awakening",
                "isVip": 2,
                "avatarUrl": "",
                "followflag": 0
            }
        }, {
            "dissid": "3823694623",
            "createtime": "2018-04-11",
            "commit_time": "2018-04-11",
            "dissname": "Classic FM 2018年度名曲Top 100",
            "imgurl": "http://p.qpic.cn/music_cover/oTVicCll2ic4QLktJAkDJRJYBiauUbdyibpQN7bEcxuIUiaick9Wz71fTgLw/600?n=1",
            "introduction": "",
            "listennum": 19535,
            "score": 0,
            "version": 0,
            "creator": {
                "type": 0,
                "qq": 2741225920,
                "encrypt_uin": "owSPoK-A7KEAon**",
                "name": "静静的顿河",
                "isVip": 0,
                "avatarUrl": "",
                "followflag": 0
            }
        }, {
            "dissid": "3793614586",
            "createtime": "2018-03-26",
            "commit_time": "2018-03-26",
            "dissname": "影视作品中的华语对唱情歌",
            "imgurl": "http://p.qpic.cn/music_cover/T0qpeJj1MpLkoxkZMuVVx9daV4Phmhlib7x2ZDicDabXGK9tQtdc60GQ/600?n=1",
            "introduction": "",
            "listennum": 73742,
            "score": 0,
            "version": 0,
            "creator": {
                "type": 2,
                "qq": 810360741,
                "encrypt_uin": "Ne6zoiCz7iv5",
                "name": "被嫌弃的唐唐的一生",
                "isVip": 2,
                "avatarUrl": "",
                "followflag": 0
            }
        }, {
            "dissid": "1150193380",
            "createtime": "2017-02-18",
            "commit_time": "2017-02-18",
            "dissname": "音乐治疗 | 潜意识助眠的α波",
            "imgurl": "http://p.qpic.cn/music_cover/eO9YLkEHAnz3gntq1uUDL4VBgp5LJuH9wcYIFcIWftqjomiaRq6bXHQ/600?n=1",
            "introduction": "",
            "listennum": 1711404,
            "score": 0,
            "version": 0,
            "creator": {
                "type": 0,
                "qq": 1057027131,
                "encrypt_uin": "oKnk7inA7i6iov**",
                "name": "Eight Weeks",
                "isVip": 0,
                "avatarUrl": "",
                "followflag": 0
            }
        }, {
            "dissid": "3697642682",
            "createtime": "2018-04-08",
            "commit_time": "2018-04-08",
            "dissname": "Future Bass：云端环绕的低音电子",
            "imgurl": "http://p.qpic.cn/music_cover/PTq9Z793Ipkz20NmN0Yky1yRwbW81Do6iaImoriaCfwCQVOaYfAxw64A/600?n=1",
            "introduction": "",
            "listennum": 452807,
            "score": 0,
            "version": 0,
            "creator": {
                "type": 0,
                "qq": 2109403575,
                "encrypt_uin": "ow6zNKvzoi4l7v**",
                "name": "Emotional",
                "isVip": 0,
                "avatarUrl": "",
                "followflag": 0
            }
        }, {
            "dissid": "3808341366",
            "createtime": "2018-04-02",
            "commit_time": "2018-04-02",
            "dissname": "穿越回古代，你想变成谁？",
            "imgurl": "http://p.qpic.cn/music_cover/KaFn5hQACzzVeLFOc4hamHHbfYPdUvJAGkWzWtQGvzjcuEWdMRF8Dw/600?n=1",
            "introduction": "",
            "listennum": 331413,
            "score": 0,
            "version": 0,
            "creator": {
                "type": 0,
                "qq": 3300733760,
                "encrypt_uin": "oiozoeSioiSson**",
                "name": "冰的唐葫芦",
                "isVip": 0,
                "avatarUrl": "",
                "followflag": 0
            }
        }, {
            "dissid": "3616302180",
            "createtime": "2017-12-26",
            "commit_time": "2017-12-26",
            "dissname": "猫咪散步时的自备乐：香港后摇",
            "imgurl": "http://p.qpic.cn/music_cover/8NYC8efIo52OTDC9przZYBglquaTPjRjBicYVbOoanOfibqp1KcuicdHw/600?n=1",
            "introduction": "",
            "listennum": 318681,
            "score": 0,
            "version": 0,
            "creator": {
                "type": 0,
                "qq": 3248641960,
                "encrypt_uin": "oi-PNeCPoKEson**",
                "name": "MouYong LynLyn",
                "isVip": 0,
                "avatarUrl": "",
                "followflag": 0
            }
        }, {
            "dissid": "3815899127",
            "createtime": "2018-04-08",
            "commit_time": "2018-04-08",
            "dissname": "Pop Metal：即兴与闷骚的律动流金",
            "imgurl": "http://p.qpic.cn/music_cover/UCJDptU3vGgQt6PS5Hn6CwOCwXOGKGyUWxzzdtoqknuTKUWHJicAcMQ/600?n=1",
            "introduction": "",
            "listennum": 99423,
            "score": 0,
            "version": 0,
            "creator": {
                "type": 2,
                "qq": 188651765,
                "encrypt_uin": "oKcF7w457iCk",
                "name": "生如夏花",
                "isVip": 2,
                "avatarUrl": "",
                "followflag": 0
            }
        }, {
            "dissid": "3805115732",
            "createtime": "2018-03-31",
            "commit_time": "2018-03-31",
            "dissname": "日本小众Hip-Hop精选",
            "imgurl": "http://p.qpic.cn/music_cover/4SToLgyAFibJLOGopcPDpxnon5jDbibcicj4PRwicO4FVXiaqPphGkaJt8A/600?n=1",
            "introduction": "",
            "listennum": 204125,
            "score": 0,
            "version": 0,
            "creator": {
                "type": 2,
                "qq": 1978787848,
                "encrypt_uin": "oKElNeSF7icPNn**",
                "name": "Extraordinary",
                "isVip": 2,
                "avatarUrl": "",
                "followflag": 0
            }
        }, {
            "dissid": "3782105549",
            "createtime": "2018-04-06",
            "commit_time": "2018-04-06",
            "dissname": "「民谣界方文山」唐眏枫填词作品",
            "imgurl": "http://p.qpic.cn/music_cover/CIY2ghIaVQwxemsbBuCNDYEKyRZqfKJxBPLRgAKicQGRhyhZXafNdHg/600?n=1",
            "introduction": "",
            "listennum": 34936,
            "score": 0,
            "version": 0,
            "creator": {
                "type": 0,
                "qq": 965669402,
                "encrypt_uin": "NKCk7wCq7enA",
                "name": "雅南",
                "isVip": 0,
                "avatarUrl": "",
                "followflag": 0
            }
        }, {
            "dissid": "3806899464",
            "createtime": "2018-04-02",
            "commit_time": "2018-04-02",
            "dissname": "迷幻Pop : 置身于缥缈世界",
            "imgurl": "http://p.qpic.cn/music_cover/tmk5HNSnJvJhsOvcIpWulbrowia33pn5l8ZBPUDDn2weUykCPKpkk9Q/600?n=1",
            "introduction": "",
            "listennum": 673328,
            "score": 0,
            "version": 0,
            "creator": {
                "type": 2,
                "qq": 2958598324,
                "encrypt_uin": "owEkNe4qNeoA7n**",
                "name": "biG橘子",
                "isVip": 2,
                "avatarUrl": "",
                "followflag": 0
            }
        }, {
            "dissid": "3637611804",
            "createtime": "2018-01-08",
            "commit_time": "2018-01-08",
            "dissname": "韩语爵士：暖流来袭，纵享别样风情",
            "imgurl": "http://p.qpic.cn/music_cover/llTQ9l2AeicK2OLIORnsUdvjFpQwHSRxibibiaQCKDy3eZGmTHu2PsaCUA/600?n=1",
            "introduction": "",
            "listennum": 434148,
            "score": 0,
            "version": 0,
            "creator": {
                "type": 2,
                "qq": 348361207,
                "encrypt_uin": "oivFoiC5ownl",
                "name": "风少",
                "isVip": 2,
                "avatarUrl": "",
                "followflag": 0
            }
        }, {
            "dissid": "3817432813",
            "createtime": "2018-04-08",
            "commit_time": "2018-04-08",
            "dissname": "Big Room House｜气氛掌控",
            "imgurl": "http://p.qpic.cn/music_cover/PiajxSqBRaEJPtLXYsvILNZR3uRic7VScwqTgUoJxjnsjPkhP5q4nUnA/600?n=1",
            "introduction": "",
            "listennum": 46276,
            "score": 0,
            "version": 0,
            "creator": {
                "type": 0,
                "qq": 4960643,
                "encrypt_uin": "7eEsoeCPoz**",
                "name": "",
                "isVip": 0,
                "avatarUrl": "",
                "followflag": 0
            }
        }, {
            "dissid": "3791579509",
            "createtime": "2018-04-08",
            "commit_time": "2018-04-08",
            "dissname": "低吟浅唱兮 | 古风诗词另类背诵法",
            "imgurl": "http://p.qpic.cn/music_cover/UCJDptU3vGgQt6PS5Hn6CwOCwXOGKGyUYql7nHIjBWL1YOeficH8AUA/600?n=1",
            "introduction": "",
            "listennum": 493061,
            "score": 0,
            "version": 0,
            "creator": {
                "type": 2,
                "qq": 188651765,
                "encrypt_uin": "oKcF7w457iCk",
                "name": "生如夏花",
                "isVip": 2,
                "avatarUrl": "",
                "followflag": 0
            }
        }, {
            "dissid": "3591424658",
            "createtime": "2017-12-06",
            "commit_time": "2017-12-06",
            "dissname": "就算听不懂也觉得浪漫的葡语对唱",
            "imgurl": "http://p.qpic.cn/music_cover/8G6Nuibex5ZabDHb3tvn3VdFYnYq82offXMvhAvn6Pib2oBNc3lBVy1A/600?n=1",
            "introduction": "",
            "listennum": 214058,
            "score": 0,
            "version": 0,
            "creator": {
                "type": 0,
                "qq": 2062275939,
                "encrypt_uin": "ownsow-l7KEiNv**",
                "name": "Lucy",
                "isVip": 0,
                "avatarUrl": "",
                "followflag": 0
            }
        }, {
            "dissid": "3808356946",
            "createtime": "2018-04-02",
            "commit_time": "2018-04-02",
            "dissname": "内地80位冷门民谣创作男歌手",
            "imgurl": "http://p.qpic.cn/music_cover/ibJJngZRP5m8ksRvDkGZxdb2EpIsEDZnKdH6rTQbWNCn9I98XdvPJUg/600?n=1",
            "introduction": "",
            "listennum": 339686,
            "score": 0,
            "version": 0,
            "creator": {
                "type": 2,
                "qq": 793407810,
                "encrypt_uin": "7iEi7enlNe6z",
                "name": "谈谈心恋恋爱 *",
                "isVip": 2,
                "avatarUrl": "",
                "followflag": 0
            }
        }, {
            "dissid": "3799489607",
            "createtime": "2018-03-28",
            "commit_time": "2018-03-28",
            "dissname": "″马刀舞曲先生″哈恰图良作品推荐",
            "imgurl": "http://p.qpic.cn/music_cover/4y7iatwYqHbpo2iaJPyJiaanuF9SeauogJveduVk9Pibria47hvMI9E5qRQ/600?n=1",
            "introduction": "",
            "listennum": 16461,
            "score": 0,
            "version": 0,
            "creator": {
                "type": 0,
                "qq": 485293608,
                "encrypt_uin": "7eckowEi7wnF",
                "name": "古典指弹大湿",
                "isVip": 0,
                "avatarUrl": "",
                "followflag": 0
            }
        }, {
            "dissid": "3762959388",
            "createtime": "2018-03-14",
            "commit_time": "2018-03-14",
            "dissname": "漫画迷不可缺少的日系少年音",
            "imgurl": "http://p.qpic.cn/music_cover/4SToLgyAFibJLOGopcPDpxqNhXX55VzuNnRuGWbSiarKwaMeLh7E2icLw/600?n=1",
            "introduction": "",
            "listennum": 133211,
            "score": 0,
            "version": 0,
            "creator": {
                "type": 2,
                "qq": 1978787848,
                "encrypt_uin": "oKElNeSF7icPNn**",
                "name": "Extraordinary",
                "isVip": 2,
                "avatarUrl": "",
                "followflag": 0
            }
        }, {
            "dissid": "3715888868",
            "createtime": "2018-02-08",
            "commit_time": "2018-02-08",
            "dissname": "蒸桑拿御用！流汗排毒时听的钢琴纯音",
            "imgurl": "http://p.qpic.cn/music_cover/MhQ4bJBPt3Yt5icXyBGNhyMrvUacQp1yLz9rocuXu2sHSFeaUnlvianQ/600?n=1",
            "introduction": "",
            "listennum": 430141,
            "score": 0,
            "version": 0,
            "creator": {
                "type": 0,
                "qq": 452775188,
                "encrypt_uin": "7e4A7iSkoKcF",
                "name": "还不是因为你长得不好看",
                "isVip": 0,
                "avatarUrl": "",
                "followflag": 0
            }
        }, {
            "dissid": "3810121575",
            "createtime": "2018-04-03",
            "commit_time": "2018-04-03",
            "dissname": "当方言邂逅古风曲调",
            "imgurl": "http://p.qpic.cn/music_cover/4Ticib0ZqQSNiayibWKtJ0wyHF9aXc0CNnqeWwaRdHibmfAfvfd9icX4dQlw/600?n=1",
            "introduction": "",
            "listennum": 74636,
            "score": 0,
            "version": 0,
            "creator": {
                "type": 0,
                "qq": 2990867470,
                "encrypt_uin": "owEqoecs7ivlon**",
                "name": "钰莞夭夭",
                "isVip": 0,
                "avatarUrl": "",
                "followflag": 0
            }
        }, {
            "dissid": "3797920236",
            "createtime": "2018-03-27",
            "commit_time": "2018-03-27",
            "dissname": "沉吟幽怨 | 惊悚古风作品",
            "imgurl": "http://p.qpic.cn/music_cover/KaFn5hQACzzVeLFOc4hamHHbfYPdUvJAPljGM0abFlic4wItjEmib2ibw/600?n=1",
            "introduction": "",
            "listennum": 75915,
            "score": 0,
            "version": 0,
            "creator": {
                "type": 0,
                "qq": 3300733760,
                "encrypt_uin": "oiozoeSioiSson**",
                "name": "冰的唐葫芦",
                "isVip": 0,
                "avatarUrl": "",
                "followflag": 0
            }
        }, {
            "dissid": "895009342",
            "createtime": "2017-12-07",
            "commit_time": "2017-12-07",
            "dissname": "女王大人！50支日系摇滚乐队女主唱",
            "imgurl": "http://p.qpic.cn/music_cover/ia3Qx5lTvNJUpQJvjpoVxFwc2iaZ1gshDehqMBR1yibZp78N98X3v6S2g/600?n=1",
            "introduction": "",
            "listennum": 227478,
            "score": 0,
            "version": 0,
            "creator": {
                "type": 0,
                "qq": 3358526560,
                "encrypt_uin": "oiokNe4A7w4son**",
                "name": "秋山陇月幸",
                "isVip": 0,
                "avatarUrl": "",
                "followflag": 0
            }
        }, {
            "dissid": "1188079779",
            "createtime": "2017-12-08",
            "commit_time": "2017-12-08",
            "dissname": "『猎奇』音乐里的“ 好好先生 ”",
            "imgurl": "http://p.qpic.cn/music_cover/T0qpeJj1MpLkoxkZMuVVx14FhY2jCS1074SD6KbXeol3aicePwaz6RQ/600?n=1",
            "introduction": "",
            "listennum": 117777,
            "score": 0,
            "version": 0,
            "creator": {
                "type": 2,
                "qq": 810360741,
                "encrypt_uin": "Ne6zoiCz7iv5",
                "name": "被嫌弃的唐唐的一生",
                "isVip": 2,
                "avatarUrl": "",
                "followflag": 0
            }
        }]
    }
}